sub2txt/cli.py
sub2txt-1.0.0.dist-info/METADATA
sub2txt-1.0.0.dist-info/WHEEL
sub2txt-1.0.0.dist-info/entry_points.txt
sub2txt-1.0.0.dist-info/top_level.txt
sub2txt-1.0.0.dist-info/RECORD
